{
	"$schema": "https://protankionline.github.io/protlvk/data/turrets-schema.json",
	"defaultTurret": {
		"id": "smoky",
		"modification": 0
	},
	"data": [
		{
			"id": "flamethrower",
			"modification": 0,
			"defaultWeapon": "flamethrower_m0"
		},
		{
			"id": "flamethrower",
			"modification": 1,
			"defaultWeapon": "flamethrower_m1"
		},
		{
			"id": "flamethrower",
			"modification": 2,
			"defaultWeapon": "flamethrower_m2"
		},
		{
			"id": "flamethrower",
			"modification": 3,
			"defaultWeapon": "flamethrower_m3"
		},
		{
			"id": "freeze",
			"modification": 0,
			"defaultWeapon": "freeze_m0"
		},
		{
			"id": "freeze",
			"modification": 1,
			"defaultWeapon": "freeze_m1"
		},
		{
			"id": "freeze",
			"modification": 2,
			"defaultWeapon": "freeze_m2"
		},
		{
			"id": "freeze",
			"modification": 3,
			"defaultWeapon": "freeze_m3"
		},
		{
			"id": "isida",
			"modification": 0,
			"defaultWeapon": "isida_m0"
		},
		{
			"id": "isida",
			"modification": 1,
			"defaultWeapon": "isida_m1"
		},
		{
			"id": "isida",
			"modification": 2,
			"defaultWeapon": "isida_m2"
		},
		{
			"id": "isida",
			"modification": 3,
			"defaultWeapon": "isida_m3"
		},
		{
			"id": "shotgun",
			"modification": 0,
			"defaultWeapon": "shotgun_m0"
		},
		{
			"id": "shotgun",
			"modification": 1,
			"defaultWeapon": "shotgun_m1"
		},
		{
			"id": "shotgun",
			"modification": 2,
			"defaultWeapon": "shotgun_m2"
		},
		{
			"id": "shotgun",
			"modification": 3,
			"defaultWeapon": "shotgun_m3"
		},
		{
			"id": "twins",
			"modification": 0,
			"defaultWeapon": "twins_m0"
		},
		{
			"id": "twins",
			"modification": 1,
			"defaultWeapon": "twins_m1"
		},
		{
			"id": "twins",
			"modification": 2,
			"defaultWeapon": "twins_m2"
		},
		{
			"id": "twins",
			"modification": 3,
			"defaultWeapon": "twins_m3"
		},
		{
			"id": "ricochet",
			"modification": 0,
			"defaultWeapon": "ricochet_m0"
		},
		{
			"id": "ricochet",
			"modification": 1,
			"defaultWeapon": "ricochet_m1"
		},
		{
			"id": "ricochet",
			"modification": 2,
			"defaultWeapon": "ricochet_m2"
		},
		{
			"id": "ricochet",
			"modification": 3,
			"defaultWeapon": "ricochet_m3"
		},
		{
			"id": "smoky",
			"modification": 0,
			"defaultWeapon": "smoky_m0"
		},
		{
			"id": "smoky",
			"modification": 1,
			"defaultWeapon": "smoky_m1"
		},
		{
			"id": "smoky",
			"modification": 2,
			"defaultWeapon": "smoky_m2"
		},
		{
			"id": "smoky",
			"modification": 3,
			"defaultWeapon": "smoky_m3"
		},
		{
			"id": "machinegun",
			"modification": 0,
			"defaultWeapon": "machinegun_m0"
		},
		{
			"id": "machinegun",
			"modification": 1,
			"defaultWeapon": "machinegun_m1"
		},
		{
			"id": "machinegun",
			"modification": 2,
			"defaultWeapon": "machinegun_m2"
		},
		{
			"id": "machinegun",
			"modification": 3,
			"defaultWeapon": "machinegun_m3"
		},
		{
			"id": "thunder",
			"modification": 0,
			"defaultWeapon": "thunder_m0"
		},
		{
			"id": "thunder",
			"modification": 1,
			"defaultWeapon": "thunder_m1"
		},
		{
			"id": "thunder",
			"modification": 2,
			"defaultWeapon": "thunder_m2"
		},
		{
			"id": "thunder",
			"modification": 3,
			"defaultWeapon": "thunder_m3"
		},
		{
			"id": "railgun",
			"modification": 0,
			"defaultWeapon": "railgun_m0"
		},
		{
			"id": "railgun",
			"modification": 1,
			"defaultWeapon": "railgun_m1"
		},
		{
			"id": "railgun",
			"modification": 2,
			"defaultWeapon": "railgun_m2"
		},
		{
			"id": "railgun",
			"modification": 3,
			"defaultWeapon": "railgun_m3"
		},
		{
			"id": "shaft",
			"modification": 1,
			"defaultWeapon": "shaft_m1"
		},
		{
			"id": "shaft",
			"modification": 0,
			"defaultWeapon": "shaft_m0"
		},
		{
			"id": "shaft",
			"modification": 2,
			"defaultWeapon": "shaft_m2"
		},
		{
			"id": "shaft",
			"modification": 3,
			"defaultWeapon": "shaft_m3"
		},
		{
			"id": "railgun_xt",
			"modification": 0,
			"defaultWeapon": "railgun_xt"
		},
		{
			"id": "railgun_xt",
			"modification": 1,
			"defaultWeapon": "railgun_xt"
		},
		{
			"id": "railgun_xt",
			"modification": 2,
			"defaultWeapon": "railgun_xt"
		},
		{
			"id": "railgun_xt",
			"modification": 3,
			"defaultWeapon": "railgun_xt"
		}
	]
}